odoo8_addon_document_no_unique_filenames-8.0.1.0.0-py2.7-nspkg.pth
odoo_addons/document_no_unique_filenames/__openerp__.py
odoo_addons/document_no_unique_filenames/__init__.py
odoo_addons/document_no_unique_filenames/README.rst
odoo_addons/document_no_unique_filenames/models/__init__.py
odoo_addons/document_no_unique_filenames/models/ir_attachment.py
odoo_addons/document_no_unique_filenames/static/description/icon.png
odoo8_addon_document_no_unique_filenames-8.0.1.0.0.dist-info/top_level.txt
odoo8_addon_document_no_unique_filenames-8.0.1.0.0.dist-info/WHEEL
odoo8_addon_document_no_unique_filenames-8.0.1.0.0.dist-info/RECORD
odoo8_addon_document_no_unique_filenames-8.0.1.0.0.dist-info/metadata.json
odoo8_addon_document_no_unique_filenames-8.0.1.0.0.dist-info/DESCRIPTION.rst
odoo8_addon_document_no_unique_filenames-8.0.1.0.0.dist-info/METADATA
odoo8_addon_document_no_unique_filenames-8.0.1.0.0.dist-info/namespace_packages.txt
